[
	{"titulo":"Patronal nacional alquiler vacacional tacha la normativa balear de disparate", "imagen":"img/img_new4.jpg", "descripcion":"El rechazo al borrador de la futura norma con la que el Govern pretende poner orden en el alquiler vacacional de pisos en las Islas traspasa fronteras. Eran conocidas las quejas y las críticas -tanto del propio sector como de partidos políticos y patronales empresariales- en la comunidad pero ayer se produjo un hecho novedoso. Más allá de los límites geográficos del archipiélago tampoco aceptan la propuesta del Pacte, que ha recibido hasta 370 alegaciones, e incluso hay quien la tilda de «disparate». Se trata de la Federación Española de Asociaciones de Viviendas y Apartamentos Turísticos (Fevitur) cuyo presidente, Pablo Zubicaray, arremetió ayer con dureza contra la reforma de la Ley prevista por el Govern. Fue con motivo del Foro Vacacional organizado por la Asociación de Apartamentos Turísticos de Baleares (Aptur) en el Parc Bit, donde mantuvo una reunión en privado con la directora general de Turismo, Pilar Carbonell.", "datetime":"10 marzo 2017 08:56"},
	{"titulo":"Cort quiere unanimidad de los vecinos para el alquiler turístico", "imgbig":"", "imgmid":"", "descripcion":"", "datetime":"18/01/2017"},
	{"titulo":"Govern elabora norma para poner orden en el alquiler turístico", "imgbig":"", "imgmid":"", "descripcion":"", "datetime":""}
]